entityshape/__init__.py
entityshape/enums.py
entityshape/exceptions.py
entityshape/models/__init__.py
entityshape/models/property_value.py
entityshape/models/result.py
entityshape/models/statement_value.py
pyentityshape-1.0.0.dist-info/LICENSE
pyentityshape-1.0.0.dist-info/METADATA
pyentityshape-1.0.0.dist-info/WHEEL
pyentityshape-1.0.0.dist-info/RECORD
